perspective_parquet/__init__.py
perspective_parquet/extension/install.json
perspective_parquet/labextension/package.json
perspective_parquet/labextension/static/169.804c1a7cf0ea9dfd1210.js
perspective_parquet/labextension/static/28.d192144fd1a9d7249be1.js
perspective_parquet/labextension/static/remoteEntry.eea45df6b9a9af71d0e1.js
perspective_parquet/labextension/static/style.js
perspective_parquet/labextension/static/third-party-licenses.json
perspective_parquet/tests/test_all.py
perspective_parquet-0.1.2.data/data/share/jupyter/labextensions/perspective-parquet/package.json
perspective_parquet-0.1.2.data/data/share/jupyter/labextensions/perspective-parquet/static/169.804c1a7cf0ea9dfd1210.js
perspective_parquet-0.1.2.data/data/share/jupyter/labextensions/perspective-parquet/static/28.d192144fd1a9d7249be1.js
perspective_parquet-0.1.2.data/data/share/jupyter/labextensions/perspective-parquet/static/remoteEntry.eea45df6b9a9af71d0e1.js
perspective_parquet-0.1.2.data/data/share/jupyter/labextensions/perspective-parquet/static/style.js
perspective_parquet-0.1.2.data/data/share/jupyter/labextensions/perspective-parquet/static/third-party-licenses.json
perspective_parquet-0.1.2.data/data/share/jupyter/labextensions/perspective-parquet/install.json
perspective_parquet-0.1.2.dist-info/METADATA
perspective_parquet-0.1.2.dist-info/WHEEL
perspective_parquet-0.1.2.dist-info/licenses/LICENSE
perspective_parquet-0.1.2.dist-info/RECORD
