Metadata-Version: 2.3
Name: perspective-parquet
Version: 0.1.2
Summary: Parquet viewer for perspective in JupyterLab
Project-URL: repository, https://github.com/timkpaine/perspective-parquet
Project-URL: homepage, https://github.com/timkpaine/perspective-parquet
Author-email: Tim Paine <t.paine154@gmail.com>
License:                                  Apache License
License-File: LICENSE
Keywords: IPython,Jupyter,JupyterLab,Widgets
Classifier: Development Status :: 4 - Beta
Classifier: Framework :: Jupyter
Classifier: Framework :: Jupyter :: JupyterLab
Classifier: License :: OSI Approved :: Apache Software License
Classifier: Programming Language :: Python
Classifier: Programming Language :: Python :: 3
Classifier: Programming Language :: Python :: 3.7
Classifier: Programming Language :: Python :: 3.8
Classifier: Programming Language :: Python :: 3.9
Classifier: Programming Language :: Python :: 3.10
Requires-Python: >=3.7
Requires-Dist: perspective-python<3,>=2
Provides-Extra: develop
Requires-Dist: black>=23; extra == 'develop'
Requires-Dist: check-manifest; extra == 'develop'
Requires-Dist: pytest; extra == 'develop'
Requires-Dist: pytest-cov; extra == 'develop'
Requires-Dist: ruff; extra == 'develop'
Provides-Extra: test
Requires-Dist: pytest; extra == 'test'
Requires-Dist: pytest-cov; extra == 'test'
